MANIFEST.in
README.md
setup.py
netw0rk/.version
netw0rk/__init__.py
netw0rk/__main__.py
netw0rk.egg-info/PKG-INFO
netw0rk.egg-info/SOURCES.txt
netw0rk.egg-info/dependency_links.txt
netw0rk.egg-info/not-zip-safe
netw0rk.egg-info/requires.txt
netw0rk.egg-info/top_level.txt
netw0rk/classes/__init__.py
netw0rk/classes/config/__init__.py
netw0rk/classes/curl/__init__.py
netw0rk/classes/firewall/__init__.py
netw0rk/classes/network/__init__.py
netw0rk/classes/utils/__init__.py