Metadata-Version: 1.0
Name: netw0rk
Version: 1.10.3
Summary: Some description.
Home-page: http://github.com/vandenberghinc/netw0rk
Author: Daan van den Bergh
Author-email: vandenberghinc.contact@gmail.com
License: MIT
Platform: UNKNOWN
